vbml/__init__.py
vbml/patcher/__init__.py
vbml/patcher/abc.py
vbml/patcher/patcher.py
vbml/pattern/__init__.py
vbml/pattern/abc.py
vbml/pattern/pattern.py
vbml/pattern/syntax.py
vbml/pattern/syntax_processing.py
vbml/pattern/validation/__init__.py
vbml/pattern/validation/ahead.py
vbml/pattern/validation/validator_parser.py
vbml/utils/__init__.py
vbml/utils/exception.py
vbml/utils/list_processing.py
vbml/utils/syntax_argument.py
vbml/validator/__init__.py
vbml/validator/abc.py
vbml/validator/default.py
vbml/validator/map.py
vbml/validator/validator.py
vbml-1.1.dist-info/LICENSE
vbml-1.1.dist-info/WHEEL
vbml-1.1.dist-info/METADATA
vbml-1.1.dist-info/RECORD
