Metadata-Version: 2.1
Name: vbml
Version: 1.1
Summary: Way to check, match & resist. Sofisticated object oriented regex-based text parser
Home-page: https://github.com/tesseradecade/vbml
License: MIT
Keywords: parser,string,string-manipulation,string-matching
Author: timoniq
Requires-Python: >=3.7,<4.0
Classifier: Environment :: Console
Classifier: Intended Audience :: Developers
Classifier: License :: OSI Approved :: MIT License
Classifier: Programming Language :: Python :: 3
Classifier: Programming Language :: Python :: 3.7
Classifier: Programming Language :: Python :: 3.8
Classifier: Topic :: Software Development :: Libraries :: Python Modules
Classifier: Topic :: Software Development :: Quality Assurance
Classifier: Typing :: Typed
Requires-Dist: typing_extensions (>=3.7.4,<4.0.0)
Project-URL: Bug Tracker, https://github.com/tesseradecade/vbml/issues
Project-URL: Repository, https://github.com/tesseradecade/vbml
